everett/__init__.py
everett/manager.py
everett/sphinxext.py
everett/ext/__init__.py
everett/ext/inifile.py
everett/ext/yamlfile.py
everett-3.5.0.dist-info/licenses/LICENSE
everett-3.5.0.dist-info/METADATA
everett-3.5.0.dist-info/WHEEL
everett-3.5.0.dist-info/top_level.txt
everett-3.5.0.dist-info/RECORD
