Metadata-Version: 2.4
Name: everett
Version: 3.5.0
Summary: Configuration library for Python applications
Author: Will Kahn-Greene
License: MPLv2
Project-URL: Homepage, https://everett.readthedocs.io/
Project-URL: Source, https://github.com/willkg/everett/
Project-URL: Issues, https://github.com/willkg/everett/issues
Keywords: conf,config,configuration,ini,env,yaml
Classifier: Development Status :: 5 - Production/Stable
Classifier: Intended Audience :: Developers
Classifier: License :: OSI Approved :: Mozilla Public License 2.0 (MPL 2.0)
Classifier: Natural Language :: English
Classifier: Programming Language :: Python :: 3 :: Only
Classifier: Programming Language :: Python :: 3.10
Classifier: Programming Language :: Python :: 3.11
Classifier: Programming Language :: Python :: 3.12
Classifier: Programming Language :: Python :: 3.13
Classifier: Programming Language :: Python :: 3.14
Classifier: Programming Language :: Python :: Implementation :: CPython
Classifier: Topic :: Software Development :: Libraries :: Python Modules
Requires-Python: >=3.10
License-File: LICENSE
Provides-Extra: sphinx
Requires-Dist: sphinx; extra == "sphinx"
Provides-Extra: ini
Requires-Dist: configobj; extra == "ini"
Provides-Extra: yaml
Requires-Dist: PyYAML; extra == "yaml"
Provides-Extra: dev
Requires-Dist: build; extra == "dev"
Requires-Dist: cogapp; extra == "dev"
Requires-Dist: mypy; extra == "dev"
Requires-Dist: pytest; extra == "dev"
Requires-Dist: ruff; extra == "dev"
Requires-Dist: tox; extra == "dev"
Requires-Dist: tox-gh-actions; extra == "dev"
Requires-Dist: tox-uv; extra == "dev"
Requires-Dist: twine; extra == "dev"
Requires-Dist: types-PyYAML; extra == "dev"
Requires-Dist: Sphinx==7.2.6; extra == "dev"
Requires-Dist: sphinx_rtd_theme; extra == "dev"
Dynamic: license-file
